evision/argus/__init__.py
evision/argus/app.py
evision/argus/coordinator.py
evision/argus/constants/__init__.py
evision/argus/constants/person.py
evision/argus/constants/record.py
evision/argus/constants/resource.py
evision/argus/constants/task.py
evision/argus/v2/__init__.py
evision/argus/v2/app.py
evision/argus/v2/coordinator.py
evision/argus/video/__init__.py
evision/argus/video/base.py
evision/argus/video/preview.py
evision/argus/video/schema.py
evision/argus/video/source.py
evision/argus/video/wrapper.py
evision/lib/__init__.py
evision/lib/config.py
evision/lib/constant.py
evision/lib/context.py
evision/lib/daemon.py
evision/lib/decorator.py
evision/lib/error.py
evision/lib/sse.py
evision/lib/db/__init__.py
evision/lib/db/_dao.py
evision/lib/db/_error.py
evision/lib/db/_field.py
evision/lib/db/_model.py
evision/lib/entity/__init__.py
evision/lib/entity/_model.py
evision/lib/log/__init__.py
evision/lib/log/dictconfig.py
evision/lib/log/logconfig.py
evision/lib/log/logutil.py
evision/lib/mixin/__init__.py
evision/lib/mixin/_property.py
evision/lib/mixin/_record.py
evision/lib/mixin/_task.py
evision/lib/parallel/__init__.py
evision/lib/parallel/_base.py
evision/lib/parallel/_process.py
evision/lib/parallel/_thread.py
evision/lib/resource/__init__.py
evision/lib/resource/cpu.py
evision/lib/resource/gpu.py
evision/lib/tornado/__init__.py
evision/lib/tornado/handler.py
evision/lib/tornado/parser.py
evision/lib/tornado/response.py
evision/lib/util/__init__.py
evision/lib/util/_cache.py
evision/lib/util/_collection.py
evision/lib/util/_draw.py
evision/lib/util/_path.py
evision/lib/util/_sys.py
evision/lib/util/redis.py
evision/lib/util/types.py
evision_lib-0.2.3.dist-info/AUTHORS.rst
evision_lib-0.2.3.dist-info/LICENSE
evision_lib-0.2.3.dist-info/METADATA
evision_lib-0.2.3.dist-info/WHEEL
evision_lib-0.2.3.dist-info/top_level.txt
evision_lib-0.2.3.dist-info/RECORD
